irispreppy/__init__.py
irispreppy/version.py
irispreppy/psf/IRIS_SG_PSFs.pkl
irispreppy/psf/IRIS_SG_deconvolve.py
irispreppy/psf/deconvolve.py
irispreppy/psf/decsave.py
irispreppy/radcal/calsave.py
irispreppy/radcal/iris_get_response.py
irispreppy/radcal/radcal.py
irispreppy/radcal/responses/iris_sra_20130211.pkl
irispreppy/radcal/responses/iris_sra_20130715.pkl
irispreppy/radcal/responses/iris_sra_c_20150331.pkl
irispreppy/radcal/responses/iris_sra_c_20161022.pkl
irispreppy/radcal/responses/iris_sra_c_20191101.pkl
irispreppy/radcal/responses/iris_sra_c_20200223.pkl
irispreppy/radcal/responses/iris_sra_c_20230223.pkl
irispreppy/radcal/responses/iris_sra_c_20230331.pkl
irispreppy/radcal/responses/iris_sra_c_20231106.pkl
irispreppy-3.1.3.dist-info/licenses/LICENSE
irispreppy-3.1.3.dist-info/METADATA
irispreppy-3.1.3.dist-info/WHEEL
irispreppy-3.1.3.dist-info/top_level.txt
irispreppy-3.1.3.dist-info/RECORD
