Metadata-Version: 2.4
Name: irispreppy
Version: 3.1.3
Summary: For radiometric calibration and point spread function deconvolution of IRIS spsetcrograph data
Home-page: https://github.com/OfAaron3/irispreppy
Author: Aaron W. Peat
Author-email: aaron.peat@uwr.edu.pl
License: MIT
License-File: LICENSE
Requires-Dist: numpy
Requires-Dist: astropy
Requires-Dist: scipy
Requires-Dist: beautifulsoup4
Requires-Dist: weno4
Dynamic: author
Dynamic: author-email
Dynamic: description
Dynamic: description-content-type
Dynamic: home-page
Dynamic: license
Dynamic: license-file
Dynamic: requires-dist
Dynamic: summary
